topsis/102103708.py
topsis/__init__.py
topsis_kartikye_102103708-1.0.1.dist-info/LICENSE
topsis_kartikye_102103708-1.0.1.dist-info/METADATA
topsis_kartikye_102103708-1.0.1.dist-info/WHEEL
topsis_kartikye_102103708-1.0.1.dist-info/entry_points.txt
topsis_kartikye_102103708-1.0.1.dist-info/top_level.txt
topsis_kartikye_102103708-1.0.1.dist-info/RECORD
