Metadata-Version: 2.1
Name: topsis-kartikye-102103708
Version: 1.0.1
Summary: A Python package to find TOPSIS for MCDM (Multi-Criteria Decision Analysis Method)
Author: Kartikye Chadda
Author-email: kartikyechadda@gmail.com
License: MIT
Keywords: TOPSIS,MCDM
Classifier: Development Status :: 5 - Production/Stable
Classifier: Intended Audience :: Developers
Classifier: Topic :: Software Development :: Build Tools
Classifier: License :: OSI Approved :: MIT License
Classifier: Programming Language :: Python :: 3
License-File: LICENSE
Requires-Dist: numpy
Requires-Dist: pandas
Requires-Dist: logging
